{
  "posts": [
    {
      "id": 1,
      "title": "json-server",
      "author": "typicode"
    }
  ],
  "alumno": [
    {
      "id": 1,
      "nombre": "pepe",
      "apellido": "Gcifuentes"
    }
  ],
  "comments": [
    {
      "id": 1,
      "body": "some comment",
      "postId": 1
    }
  ],
  "casas": [
    {
      "nombre": "Pazo oubiño",
      "precio": 500000,
      "alquiler": false,
      "habitaciones": 5,
      "foto": "https://www.hola.com/imagenes/actualidad/20180216120517/familia-franco-pone-venta-pazo-meiras/0-539-996/pazo-meiras-t.jpg",
      "direccion": "Calle la felicidad, n4 Vigo - 48657",
      "servicios": [
        {
          "nombre": "tv",
          "disponible": true
        },
        {
          "nombre": "wc",
          "disponible": true
        },
        {
          "nombre": "jardin",
          "disponible": true
        },
        {
          "nombre": "cocina",
          "disponible": true
        }
      ]
    },
    {
      "nombre": "Santutxu",
      "precio": 600,
      "alquiler": true,
      "habitaciones": 3,
      "foto": "https://d.inmofactory.com/1/98366/13970473/165256531.jpg/300x225/a_fill/",
      "direccion": "Mazustegi 9, Bilbao - 4800",
      "servicios": [
        {
          "nombre": "tv",
          "disponible": true
        },
        {
          "nombre": "wc",
          "disponible": true
        },
        {
          "nombre": "jardin",
          "disponible": false
        },
        {
          "nombre": "cocina",
          "disponible": true
        }
      ]
    }
  ],
  "todos": [
    {
      "userId": -1,
      "title": "Aprender Angular 2.5",
      "completed": false,
      "id": 3
    },
    {
      "userId": -1,
      "title": "nueva",
      "completed": true,
      "id": 5
    },
    {
      "userId": -1,
      "title": "assasasa",
      "completed": true,
      "id": 6
    }
  ],
  "recetas": [
    {
      "id": 1,
      "nombre": "Marmitako",
      "descripcion": "Lorem ipsum dolor sit amet, consectetur adipiscing elit. Nunc posuere, leo id lobortis scelerisque, nisi mi placerat dui, sit amet molestie velit enim at nunc. Nam ultricies est ac quam feugiat porttitor. In non consequat libero, vel suscipit libero. Donec vel lectus purus. Etiam ut elementum lectus. Proin rutrum suscipit ultricies. Nullam maximus velit justo, nec lacinia est dignissim in. Ut lacinia augue pellentesque tincidunt sollicitudin. Ut eu iaculis massa. Nunc iaculis est in lectus pretium, eu porta odio placerat. Maecenas nibh purus, mollis in elementum at, faucibus eu justo. Aliquam justo arcu, dictum vitae maximus sed, luctus et nunc.                            Etiam ut est id ante porta varius. Cras blandit lectus id lectus finibus, in venenatis neque porta. Pellentesque et consectetur tellus. Nulla nec odio leo. Mauris sed placerat dolor. Phasellus porta nec urna in porta. Duis faucibus et diam sit amet cursus. In varius sollicitudin massa. Nullam mattis velit sed lectus hendrerit, quis malesuada nibh cursus. Vestibulum vestibulum sapien ac neque tempor, sit amet scelerisque dolor sollicitudin. Suspendisse quis arcu et eros tincidunt volutpat quis vitae lacus. Phasellus pretium commodo sapien, non accumsan nisi egestas nec. Etiam ante purus, luctus eget orci vel, accumsan lobortis nulla. Curabitur posuere turpis lacus, ac sodales mauris accumsan in.Nam dapibus dui nec augue ornare egestas. Maecenas efficitur lacinia metus in aliquet. Class aptent taciti sociosqu ad litora torquent per conubia nostra, per inceptos himenaeos. Duis consectetur, lectus iaculis vulputate congue, arcu enim tincidunt felis, ut bibendum magna quam eget ipsum. Curabitur nec est a ipsum ornare efficitur venenatis non erat. Quisque rhoncus leo et ultrices vestibulum. Quisque viverra libero sit amet nunc porttitor, a dignissim mi luctus. Aenean ut augue tempor, ullamcorper nibh ac, fringilla massa. Aliquam sollicitudin ipsum enim, a gravida neque cursus eu. Proin commodo felis interdum arcu tincidunt laoreet ac a ipsum. Pellentesque habitant morbi tristique senectus et netus et malesuada fames ac turpis egestas. Etiam scelerisque ligula sed est porta, nec tincidunt mi placerat. Pellentesque sollicitudin ante dapibus tortor condimentum, et rutrum quam blandit. Donec id tincidunt elit. Integer id ultricies ex. Aliquam erat volutpat.",
      "imagen": "https://unareceta.com/wp-content/uploads/2016/08/receta-marmitako-de-verduras.jpg",
      "likes": "24",
      "isGlutenFree": true,
      "cocinero": "Robin Food",
      "ingredientes": [
        "patata",
        "bonito",
        "pimientos",
        "cebolla"
      ]
    },
    {
      "id": 2,
      "nombre": "Bacalao al pil-pil",
      "descripcion": "El bacalao al pil-pil es un plato tradicional español típico de la cocina vasca elaborado con cuatro ingredientes básicos: bacalao, aceite de oliva, ajo y pimientos guindillas.",
      "imagen": "https://www.miscosillasdecocina.com/wp-content/uploads/2014/02/bacalao-pilpil-e1491084486535.jpg",
      "likes": "32",
      "isGlutenFree": true,
      "cocinero": "Karlos Arguiñano",
      "ingredientes": [
        "bacalao",
        "aceite",
        "ajo",
        "guindilla"
      ]
    },
    {
      "id": 3,
      "nombre": "Falafel",
      "descripcion": "El faláfel o falafel es una croqueta de garbanzos o haba y se originó en algún lugar del subcontinente indio.",
      "imagen": "http://recetasarabes.com/wp-content/img-recetas-arabes/2012/03/xfalafel-3-500x262.jpg.pagespeed.ic.HYdrSUMpct.webp",
      "likes": "12",
      "isGlutenFree": false,
      "cocinero": "Ivan Surinder",
      "ingredientes": [
        "garbanzos",
        "cebolla",
        "aceite",
        "comino",
        "perejil",
        "pimienta"
      ]
    },
    {
      "id": 4,
      "nombre": "Talo",
      "descripcion": "El talo es un plato típico del País Vasco, Navarra y País Vasco francés similar a la arepa de Colombia y Venezuela o a una tortilla de maíz grande de México.",
      "imagen": "https://www.euskadi-basquecountry.org/blog/wp-content/uploads/2015/02/talo-JB-argazkiak.jpg",
      "likes": "27",
      "isGlutenFree": false,
      "cocinero": "Amama",
      "ingredientes": [
        "txistorra",
        "harina",
        "queso",
        "aceite"
      ]
    },
    {
      "id": 5,
      "nombre": "Sushi",
      "descripcion": "Plato de origen japonés basado en arroz que se acompaña en general con: sésamo, salmón o trucha, dependiendo de los gustos puede estar crudo o ahumado, adobado con vinagre de arroz, azúcar, sal y otros ingredientes, como verduras, pescados o mariscos.",
      "imagen": "https://enlacocina.telemesa.es/wp-content/uploads/2018/02/sushi.jpg",
      "likes": "72",
      "isGlutenFree": true,
      "cocinero": "Itamae",
      "ingredientes": [
        "arroz",
        "sésamo",
        "salmón",
        "vinagre de arroz",
        "verdura"
      ]
    },
    {
      "id": 6,
      "nombre": "Fajitas",
      "descripcion": "La fajita es uno de los platos más tradicionales y populares de la cocina texana. Consiste en carne asada a la parrilla y cortada en tiras, servida sobre una tortilla de harina de maíz o harina de trigo.",
      "imagen": "https://unareceta.com/wp-content/uploads/2016/08/receta-fajitas-de-carne-picada-640x417.jpg",
      "likes": "58",
      "isGlutenFree": false,
      "cocinero": "Pablo Escobar",
      "ingredientes": [
        "pechuga",
        "cebolla",
        "pimientos",
        "tomate"
      ]
    },
    {
      "nombre": "Rabo de toro",
      "descripcion": "El rabo de toro al estilo cordobés es uno de los platos más tradicionales no solo de Córdoba, sino también de Andalucía, convirtiéndose en uno de los clásicos de la gastronomía española.",
      "imagen": "https://unareceta.com/wp-content/uploads/2015/01/receta-de-rabo-de-toro-al-estilo-cordobe%CC%81s-640x427.jpg",
      "likes": "24",
      "isGlutenFree": false,
      "cocinero": "Pedro Subijana",
      "ingredientes": [
        "patata",
        "rabo de toro",
        "pimientos",
        "cebolla",
        "zanahoria"
      ],
      "id": 7
    },
    {
      "id": 8,
      "nombre": "Ensalada",
      "imagen": "https://www.hogarmania.com/archivos/201912/ensalada-cebolleta-xl-668x400x80xX-1.jpg",
      "likes": 30,
      "cocinero": "Karlos Arguiñano",
      "descripcion": "La ensalada a base de lechugas y cebolleta equilibra la comida de hoy al mejorar la presencia de verduras y hortalizas. Además esta ensalada mejora también la digestión del plato principal. Por la presencia de vitamina C, esta ensalada mejora la asimilación del hierro de la carne del plato principal. Las aceitunas son un alimento muy nutritivo (mas las negras que las verdes). Son frutos grasos, siendo su grasa monoinsaturada, rica en ácido oléico (es la grasa del aceite de oliva) que ayuda a bajar el colesterol. También aportan fibra que nos ayuda a prevenir el estreñimiento. La ración recomendable son 40 gr por comensal. De postre una fruta y un yogur.",
      "isGlutenFree": true,
      "ingredientes": [
        "lechuga",
        "cebolleta",
        "aceitunas",
        "vinagre",
        "aceite",
        "sal"
      ]
    },
    {
      "id": 9,
      "nombre": "Merluza en salsa con guisantes y almejas",
      "imagen": "https://www.hogarmania.com/archivos/201105/merluza-en-salsa-con-guisantes-y-almejas-xl-668x400x80xX.jpg",
      "likes": 100,
      "cocinero": "Eva Arguiñano",
      "descripcion": "Pon el huevo a cocer en abundante agua durante 8 minutos. Déjalo templar, pélalo, pártelo por la mitad y reserva. Retira la parte dura de los espárragos y saltéalos a fuego lento en una sartén con un poco de aceite. Reserva. Pica finamente el puerro y póchalo en una sartén con un poco de aceite. Sazona. Cuando el puerro empiece a ablandarse, añade el ajo picado. Cuando todo esté bien doradito, incorpora la harina y rehoga un poco. Añade el vino y un poco de agua. Rectifica de sal y añade los gui",
      "isGlutenFree": true,
      "ingredientes": [
        "merluza",
        "almejas",
        "guisantes",
        "esparragos",
        "huevos",
        "perejil"
      ]
    },
    {
      "id": 10,
      "nombre": "Tostadas de Carnaval",
      "imagen": "https://vod-hogarmania.atresmedia.com/hogarmania/images/images01/2013/06/13/5c00e43316334d000191932a/1239x697.jpg",
      "likes": 0,
      "cocinero": "Eva Arguiñano",
      "descripcion": "Pon la leche y la nata a calentar con la rama de canela y 120 gramos de azúcar. Retira del fuego y viértela sobre las rebanadas de pan en un recipiente hondo. Deja que se empapen bien. En una sartén con abundante aceite, añade un trozo de cáscara de limón. Escurre un poco las torrijas, pásalas por huevo batido y fríelas en la sartén. Retira a un plato con papel absorbente para eliminar el exceso de aceite. Mezcla el resto de azúcar con la canela en polvo y espolvorea por encima de las torrijas",
      "isGlutenFree": false,
      "ingredientes": [
        "rebanadas de pan",
        "leche",
        "azucar",
        "canela",
        "huevo",
        "limon"
      ]
    }
  ],
  "profile": {
    "name": "typicode"
  }
}